.gitignore
LICENSE
README.md
setup.cfg
setup.py
example/panda_rain_dance.py
pyboolet/__init__.py
pyboolet/constraint.py
pyboolet/context.py
pyboolet/default_physics_client_manager.py
pyboolet/physics_client.py
pyboolet/shape.py
pyboolet/simulation_component.py
pyboolet.egg-info/PKG-INFO
pyboolet.egg-info/SOURCES.txt
pyboolet.egg-info/dependency_links.txt
pyboolet.egg-info/requires.txt
pyboolet.egg-info/top_level.txt
pyboolet/multibody/__init__.py
pyboolet/multibody/box.py
pyboolet/multibody/multibody.py
pyboolet/multibody/simple_body.py
pyboolet/multibody/sphere.py
pyboolet/multibody/urdf_body.py
pyboolet/simulation_object/__init__.py
pyboolet/simulation_object/contact_point.py
pyboolet/simulation_object/joint.py
pyboolet/simulation_object/link.py
pyboolet/simulation_object/revolute_joint.py
pyboolet/simulation_object/simulation_object.py
pyboolet/util/__init__.py
pyboolet/util/common.py
pyboolet/util/read_only_dict.py
pyboolet/util/read_only_ordered_dict.py