Metadata-Version: 2.1
Name: pyboolet
Version: 1.0.1
Summary: Object-oriented wrapper for pybullet.
Home-page: https://github.com/TimSchneider42/pyboolet
Author: Tim Schneider
Author-email: schneider@ias.informatik.tu-darmstadt.de
License: MIT
Platform: UNKNOWN
Classifier: Intended Audience :: Science/Research
Classifier: License :: OSI Approved :: MIT License
Classifier: Operating System :: POSIX :: Linux
Classifier: Programming Language :: Python :: 3.6
